kmon/__init__.py
kmon/kmonapi.py
kmon-0.1.6.dist-info/LICENSE
kmon-0.1.6.dist-info/METADATA
kmon-0.1.6.dist-info/WHEEL
kmon-0.1.6.dist-info/top_level.txt
kmon-0.1.6.dist-info/RECORD
