Metadata-Version: 2.1
Name: kmon
Version: 0.1.6
Summary: Korea University Monitoring System
Home-page: https://gitlab.com/twinlab/korea-monitoring-system
Author: sjj&jmj
Author-email: sjj@twinlab.co.kr
License: UNKNOWN
Platform: UNKNOWN
Classifier: Programming Language :: Python :: 3
Classifier: License :: OSI Approved :: MIT License
Classifier: Operating System :: OS Independent
Requires-Python: >=3.6
